sweet/__init__.py
sweet/__main__.py
sweet/cli.py
sweet/core/__init__.py
sweet/core/transforms.py
sweet/core/workbook.py
sweet/integrations/__init__.py
sweet/ui/__init__.py
sweet/ui/app.py
sweet/ui/sweet.tcss
sweet/ui/widgets.py
sweet_data-0.30.dist-info/licenses/LICENSE
sweet_data-0.30.dist-info/METADATA
sweet_data-0.30.dist-info/WHEEL
sweet_data-0.30.dist-info/entry_points.txt
sweet_data-0.30.dist-info/top_level.txt
sweet_data-0.30.dist-info/RECORD
