Metadata-Version: 2.4
Name: sweet-data
Version: 0.30
Summary: An interactive console application for data manipulation
Author-email: Richard Iannone <riannone@me.com>
License: MIT License
Project-URL: homepage, https://github.com/rich-iannone/sweet-data
Keywords: data-engineering,textual,polars,cli,interactive,data-manipulation
Classifier: Development Status :: 3 - Alpha
Classifier: Environment :: Console
Classifier: Intended Audience :: Developers
Classifier: License :: OSI Approved :: MIT License
Classifier: Operating System :: OS Independent
Classifier: Programming Language :: Python :: 3
Classifier: Programming Language :: Python :: 3.10
Classifier: Programming Language :: Python :: 3.11
Classifier: Programming Language :: Python :: 3.12
Classifier: Topic :: Software Development :: Libraries :: Python Modules
Classifier: Topic :: Scientific/Engineering :: Information Analysis
Requires-Python: >=3.10
License-File: LICENSE
Requires-Dist: textual>=0.41.0
Requires-Dist: polars>=1.32.0
Requires-Dist: duckdb>=0.9.0
Requires-Dist: rich>=13.0.0
Requires-Dist: click>=8.0.0
Requires-Dist: tree-sitter-python>=0.23.6
Requires-Dist: chatlas>=0.9.2
Requires-Dist: anthropic>=0.62.0
Dynamic: license-file
